ez_agent/__init__.py
ez_agent/py.typed
ez_agent/types.py
ez_agent/agent/agent.py
ez_agent/agent/agent_async.py
ez_agent/agent/base_tool.py
ez_agent/agent/function_tool.py
ez_agent/agent/mcp_tool.py
ez_agent/prefabs/__init__.py
ez_agent/prefabs/function_tools.py
ez_agent_ark-0.2.0a0.dist-info/licenses/LICENSE
ez_agent_ark-0.2.0a0.dist-info/METADATA
ez_agent_ark-0.2.0a0.dist-info/WHEEL
ez_agent_ark-0.2.0a0.dist-info/top_level.txt
ez_agent_ark-0.2.0a0.dist-info/RECORD
