Metadata-Version: 2.4
Name: ez_agent_ark
Version: 0.2.0a0
Summary: 基于 volcengine-python-sdk 的简单 AI Agent 框架
Author-email: captainSuo <captainsuo@outlook.com>
Project-URL: Homepage, https://github.com/captainSuo/ez-agent
Classifier: Programming Language :: Python :: 3.13
Classifier: License :: OSI Approved :: MIT License
Requires-Python: >=3.13
License-File: LICENSE
Requires-Dist: mcp[cli]>=1.9.2
Requires-Dist: volcengine-python-sdk[ark]>=4.0.9
Dynamic: license-file
